{"attributes":{},"extra_attributes":{"version":24,"type":"ap_lane_2d_dmyscdx","taskId":"2784","dataId":"427"},"bundles":[{"attributes":{"id":"0","invalid":false},"extra_attributes":{"keyFrame":true,"bundleFileName":"front_fisheye_camera_1692148626575428337.json"},"groups":[{"type":"lane","attributes":{"id":"0"},"extra_attributes":{"createUserId":"787","createTimestamp":1692867470551},"objects":[{"type":"lane_fisheye_front_left_rear_right_bev_box","geometry":"polygon","sensor":"fisheye_front_left_rear_right_bev","attributes":{"id":"0","position":{"x":144.27672330677433,"y":652.2142775895427},"dimension":{"width":559.0653923947094,"height":317.6421043899543}},"extra_attributes":{"createUserId":"787","createTimestamp":1692867470553,"updateUserId":"787","updateTimestamp":1692867473971,"generateMode":1,"isLeave":false},"points":[{"x":704.3421157014837,"y":653.2142775895427,"attributes":{"id":"eef0f9d9026942538241332e5c498beb"},"extra_attributes":{"createUserId":"787","createTimestamp":1692867470555,"updateUserId":"787","updateTimestamp":1692867473969}},{"x":559.8533952569405,"y":727.1101872327288,"attributes":{"id":"5ce60b814ad4463d9bb5e8760a43abe4"},"extra_attributes":{"createUserId":"787","createTimestamp":1692867470555,"updateUserId":"787","updateTimestamp":1692867473969}},{"x":440.7432836891035,"y":794.3885516612347,"attributes":{"id":"fdacd7510ed74ee38616074a67cfb3dc"},"extra_attributes":{"createUserId":"787","createTimestamp":1692867470555,"updateUserId":"787","updateTimestamp":1692867473969}},{"x":352.54431044064705,"y":851.74059651467,"attributes":{"id":"030bcfed2f774dbab3a7fbaa006598ba"},"extra_attributes":{"createUserId":"787","createTimestamp":1692867470555,"updateUserId":"787","updateTimestamp":1692867473969}},{"x":263.24285002658485,"y":921.2248047024857,"attributes":{"id":"902517307e024a5ca9c1ff3e02e112d0"},"extra_attributes":{"createUserId":"787","createTimestamp":1692867470555,"updateUserId":"787","updateTimestamp":1692867473969}},{"x":203.70854308387675,"y":970.856381979497,"attributes":{"id":"07f8d001044c402282761bbdc68b9e90"},"extra_attributes":{"createUserId":"787","createTimestamp":1692867470555,"updateUserId":"787","updateTimestamp":1692867473969}},{"x":145.27672330677433,"y":899.1663259127029,"attributes":{"id":"5476590f9845436fa92233f4f5551370"},"extra_attributes":{"createUserId":"787","createTimestamp":1692867470555,"updateUserId":"787","updateTimestamp":1692867473969}},{"x":251.1154912049221,"y":827.4762698459089,"attributes":{"id":"a4d3ab9231fe4d7285dcb163a6fcdbdc"},"extra_attributes":{"createUserId":"787","createTimestamp":1692867470555,"updateUserId":"787","updateTimestamp":1692867473969}},{"x":356.9542591030699,"y":763.5066813555388,"attributes":{"id":"bbcb70616810494c97013b9c24351a1b"},"extra_attributes":{"createUserId":"787","createTimestamp":1692867470555,"updateUserId":"787","updateTimestamp":1692867473969}},{"x":448.2297561198109,"y":720.2310809193064,"attributes":{"id":"39d25134493d4a96abdc77622e9d530f"},"extra_attributes":{"createUserId":"787","createTimestamp":1692867470555,"updateUserId":"787","updateTimestamp":1692867473969}},{"x":558.7094104089141,"y":671.9639943779403,"attributes":{"id":"5f0cf5b8b1d04ca2b32880e0ed596915"},"extra_attributes":{"createUserId":"787","createTimestamp":1692867470555,"updateUserId":"787","updateTimestamp":1692867473969}},{"x":599.5014355363252,"y":659.8318310435598,"attributes":{"id":"6a50c6a62ea643539af40fd469dfa166"},"extra_attributes":{"createUserId":"787","createTimestamp":1692867470555,"updateUserId":"787","updateTimestamp":1692867473969}}]}]},{"type":"ignore","attributes":{"id":"3"},"extra_attributes":{"createUserId":"787","createTimestamp":1692867500423},"objects":[{"type":"ignore_fisheye_front_left_rear_right_bev_box","geometry":"polygon","sensor":"fisheye_front_left_rear_right_bev","attributes":{"id":"3","position":{"x":1477.1922825065096,"y":650.7058445989808},"dimension":{"width":396.1938939385743,"height":195.4524061753575}},"extra_attributes":{"createUserId":"787","createTimestamp":1692867500424,"updateUserId":"787","updateTimestamp":1692867500425,"generateMode":1,"isLeave":false},"points":[{"x":1478.1922825065096,"y":651.7058445989808,"attributes":{"id":"657a9340f1f44a539e72cc22a7c5193c"},"extra_attributes":{"createUserId":"787","createTimestamp":1692867500424}},{"x":1499.3629485948304,"y":663.2030449622372,"attributes":{"id":"9f53a591a14e412a98621bbe257185dc"},"extra_attributes":{"createUserId":"787","createTimestamp":1692867500424}},{"x":1866.5227861837077,"y":847.1582507743383,"attributes":{"id":"56d55a03de884f77b9762615047357f1"},"extra_attributes":{"createUserId":"787","createTimestamp":1692867500424}},{"x":1874.386176445084,"y":651.7058445989808,"attributes":{"id":"2e7e7794bb834061ab91eecafb15021a"},"extra_attributes":{"createUserId":"787","createTimestamp":1692867500424}}]}]},{"type":"ignore","attributes":{"id":"4"},"extra_attributes":{"createUserId":"787","createTimestamp":1692867510855},"objects":[{"type":"ignore_fisheye_front_left_rear_right_bev_box","geometry":"polygon","sensor":"fisheye_front_left_rear_right_bev","attributes":{"id":"4","position":{"x":77.11217741431481,"y":515.9320365222093},"dimension":{"width":614.1565525290589,"height":215.070165088718}},"extra_attributes":{"createUserId":"787","createTimestamp":1692867510855,"updateUserId":"787","updateTimestamp":1692867510857,"generateMode":1,"isLeave":false},"points":[{"x":692.2687299433737,"y":580.901621900915,"attributes":{"id":"3f9620b03d0346668a72220872d2326a"},"extra_attributes":{"createUserId":"787","createTimestamp":1692867510856}},{"x":317.4230936374332,"y":732.0022016109273,"attributes":{"id":"06b08746ed424820a50ed7b6ef171504"},"extra_attributes":{"createUserId":"787","createTimestamp":1692867510856}},{"x":78.11217741431481,"y":638.2536698660147,"attributes":{"id":"c779c74a7599460580644fba2faf2b1d"},"extra_attributes":{"createUserId":"787","createTimestamp":1692867510856}},{"x":478.31501852918666,"y":516.9320365222093,"attributes":{"id":"dce05c74a58a49d684c481f39528ff96"},"extra_attributes":{"createUserId":"787","createTimestamp":1692867510856}}]}]},{"type":"ignore","attributes":{"id":"5"},"extra_attributes":{"createUserId":"787","createTimestamp":1692867510858},"objects":[{"type":"ignore_fisheye_front_left_rear_right_bev_box","geometry":"polygon","sensor":"fisheye_front_left_rear_right_bev","attributes":{"id":"5","position":{"x":769.3534439693462,"y":423.11634029223546},"dimension":{"width":527.7734324913024,"height":171.72247049737052}},"extra_attributes":{"createUserId":"787","createTimestamp":1692867510859,"updateUserId":"787","updateTimestamp":1692867510860,"generateMode":1,"isLeave":false},"points":[{"x":770.3534439693462,"y":576.6161461816914,"attributes":{"id":"2487d088f0b54a75a482d551e463bf8a"},"extra_attributes":{"createUserId":"787","createTimestamp":1692867510859}},{"x":1298.1268764606486,"y":595.838810789606,"attributes":{"id":"a310c0c644d44c329be5b9ab44e79e21"},"extra_attributes":{"createUserId":"787","createTimestamp":1692867510859}},{"x":1281.47383126068,"y":424.11634029223546,"attributes":{"id":"7040d66ef1394a8d8a06a1ac63acdeba"},"extra_attributes":{"createUserId":"787","createTimestamp":1692867510859}}]}]},{"type":"stop_line","attributes":{"id":"6"},"extra_attributes":{"createUserId":"787","createTimestamp":1692867539098},"objects":[{"type":"stop_line_fisheye_front_left_rear_right_bev_box","geometry":"polygon","sensor":"fisheye_front_left_rear_right_bev","attributes":{"id":"6","position":{"x":607.6740489746918,"y":637.9320830889035},"dimension":{"width":888.1144755765961,"height":23.678060183247453}},"extra_attributes":{"createUserId":"787","createTimestamp":1692867539099,"updateUserId":"787","updateTimestamp":1692867567419,"generateMode":1,"isLeave":false},"points":[{"x":608.6740489746917,"y":658.033344027591,"attributes":{"id":"74fa2d00dc7043b3ae499324fbb077ba"},"extra_attributes":{"createUserId":"787","createTimestamp":1692867539099,"updateUserId":"787","updateTimestamp":1692867567418}},{"x":780.3323927699325,"y":653.6440472806919,"attributes":{"id":"360f8353235342238f8895db506e393f"},"extra_attributes":{"createUserId":"787","createTimestamp":1692867539099,"updateUserId":"787","updateTimestamp":1692867567418}},{"x":966.879947904069,"y":647.4040161732162,"attributes":{"id":"0a0402bd065345dd95596b8d4bb4fbc7"},"extra_attributes":{"createUserId":"787","createTimestamp":1692867539099,"updateUserId":"787","updateTimestamp":1692867567418}},{"x":1224.5778992071496,"y":648.9759158489127,"attributes":{"id":"4e0b87bf3ae148c9802db000830d83d3"},"extra_attributes":{"createUserId":"787","createTimestamp":1692867539099,"updateUserId":"787","updateTimestamp":1692867567418}},{"x":1390.4469742328934,"y":654.4508333807919,"attributes":{"id":"661aec2153fe48459a83af26b42423c7"},"extra_attributes":{"createUserId":"787","createTimestamp":1692867539099,"updateUserId":"787","updateTimestamp":1692867567418}},{"x":1496.7885245512878,"y":662.6101432721509,"attributes":{"id":"b280c0439eb14f7a9b0cf49052e0658b"},"extra_attributes":{"createUserId":"787","createTimestamp":1692867539099,"updateUserId":"787","updateTimestamp":1692867567418}},{"x":1476.902088001141,"y":653.0862690759843,"attributes":{"id":"2e84b2d6d9c847c59af4238ad6f5455a"},"extra_attributes":{"createUserId":"787","createTimestamp":1692867539099,"updateUserId":"787","updateTimestamp":1692867567418}},{"x":1221.5911282268967,"y":639.6800581713773,"attributes":{"id":"cb941662535e40ce9ae15ed124cb7d90"},"extra_attributes":{"createUserId":"787","createTimestamp":1692867557820,"updateUserId":"787","updateTimestamp":1692867567418}},{"x":901.0493561828209,"y":638.9320830889035,"attributes":{"id":"fc081de59a2448729aa77f49d421c453"},"extra_attributes":{"createUserId":"787","createTimestamp":1692867539099,"updateUserId":"787","updateTimestamp":1692867567418}},{"x":629.4855812898102,"y":649.3473866797046,"attributes":{"id":"2b6ea56e0c694b8db9409b413287ba85"},"extra_attributes":{"createUserId":"787","createTimestamp":1692867539099,"updateUserId":"787","updateTimestamp":1692867567418}}]}]},{"type":"lane","attributes":{"id":"7"},"extra_attributes":{"createUserId":"787","createTimestamp":1692867547133},"objects":[{"type":"lane_fisheye_front_left_rear_right_bev_box","geometry":"polygon","sensor":"fisheye_front_left_rear_right_bev","attributes":{"id":"7","position":{"x":631.9152096690733,"y":609.0199316929386},"dimension":{"width":171.85622581189443,"height":36.39482362347144}},"extra_attributes":{"createUserId":"787","createTimestamp":1692867547135,"updateUserId":"787","updateTimestamp":1692867547152,"generateMode":1,"isLeave":false},"points":[{"x":804.7714354809677,"y":610.0199316929386,"attributes":{"id":"acd38985c42d475bb61ad264f5db0c95"},"extra_attributes":{"createUserId":"787","createTimestamp":1692867547137}},{"x":727.0943424975924,"y":644.4474674513015,"attributes":{"id":"474be7bab62c4b94ba34c6527b22e763"},"extra_attributes":{"createUserId":"787","createTimestamp":1692867547137}},{"x":632.9152096690733,"y":646.41475531641,"attributes":{"id":"1320ad85271c4a3bb02b76ee4c2ea8ad"},"extra_attributes":{"createUserId":"787","createTimestamp":1692867547137}},{"x":740.8273736554713,"y":611.0035756792369,"attributes":{"id":"437d756704e649c4973f1b1596464252"},"extra_attributes":{"createUserId":"787","createTimestamp":1692867547137}}]}]},{"type":"lane","attributes":{"id":"8"},"extra_attributes":{"createUserId":"787","createTimestamp":1692867585575},"objects":[{"type":"lane_fisheye_front_left_rear_right_bev_box","geometry":"polygon","sensor":"fisheye_front_left_rear_right_bev","attributes":{"id":"8","position":{"x":1188.1615756533731,"y":648.8416083171544},"dimension":{"width":510.3424513736811,"height":279.1559896517439}},"extra_attributes":{"createUserId":"787","createTimestamp":1692867585575,"updateUserId":"787","updateTimestamp":1692867585578,"generateMode":1,"isLeave":false},"points":[{"x":1189.1615756533731,"y":649.8416083171544,"attributes":{"id":"bd8246ce63d64d71b3d2ac8f1024b23d"},"extra_attributes":{"createUserId":"787","createTimestamp":1692867585576}},{"x":1333.6755048064645,"y":712.6020299402257,"attributes":{"id":"bd815cd88c6649a3b2979345a0ca0187"},"extra_attributes":{"createUserId":"787","createTimestamp":1692867585576}},{"x":1498.2792382838393,"y":800.9845843905363,"attributes":{"id":"53ede5b9060d4a5c9215598a25952596"},"extra_attributes":{"createUserId":"787","createTimestamp":1692867585576}},{"x":1584.3606075309888,"y":856.2896248746486,"attributes":{"id":"0d14637be36340c1a708fa48ed107889"},"extra_attributes":{"createUserId":"787","createTimestamp":1692867585576}},{"x":1690.5212070663683,"y":928.9975979688983,"attributes":{"id":"3f580f15081e46baa0ebbfbf09134a1d"},"extra_attributes":{"createUserId":"787","createTimestamp":1692867585576}},{"x":1699.5040270270542,"y":912.65872761064,"attributes":{"id":"72c98c7e59174c6a97cbe3b01214b758"},"extra_attributes":{"createUserId":"787","createTimestamp":1692867585576}},{"x":1541.876307371978,"y":808.0899552077294,"attributes":{"id":"effe1a5da5ef472e87b7176644c3152d"},"extra_attributes":{"createUserId":"787","createTimestamp":1692867585576}},{"x":1377.6784190413198,"y":720.6769953824933,"attributes":{"id":"742f734453fd4548af9e2f60f8f2daa2"},"extra_attributes":{"createUserId":"787","createTimestamp":1692867585576}},{"x":1210.8467269827638,"y":650.9849439714206,"attributes":{"id":"ece757bd5c5a4501b6e09bbed9ff9c95"},"extra_attributes":{"createUserId":"787","createTimestamp":1692867585576}}]}]},{"type":"roadmark_other","attributes":{"id":"9"},"extra_attributes":{"createUserId":"787","createTimestamp":1694065883317},"objects":[{"type":"roadmark_other_fisheye_front_left_rear_right_bev_box","geometry":"polygon","sensor":"fisheye_front_left_rear_right_bev","attributes":{"id":"9","position":{"x":812.6269699267534,"y":651.2202144329418},"dimension":{"width":259.53157343430144,"height":393.38995787753845}},"extra_attributes":{"createUserId":"787","createTimestamp":1694065883318,"updateUserId":"787","updateTimestamp":1694065883321,"generateMode":1,"isLeave":false},"points":[{"x":1073.1585433610549,"y":721.4987935002135,"attributes":{"id":"5bfff7d00fdd40ebb1a26e69fab5d9a8"},"extra_attributes":{"createUserId":"787","createTimestamp":1694065883318}},{"x":1021.449418539725,"y":894.3703026069932,"attributes":{"id":"3a0ba09ead2b49f3aa321f7f8798ed19"},"extra_attributes":{"createUserId":"787","createTimestamp":1694065883318}},{"x":974.3348250705384,"y":1044.3012714763363,"attributes":{"id":"7c150d07215044b1a791290d969a0dce"},"extra_attributes":{"createUserId":"787","createTimestamp":1694065883318}},{"x":970.4090926201052,"y":1045.6101723104803,"attributes":{"id":"7153bf95c405469b8815153eb39b8f65"},"extra_attributes":{"createUserId":"787","createTimestamp":1694065883318}},{"x":938.348944274901,"y":986.0551843569262,"attributes":{"id":"f35b5850eace4bfaa979b6b0f4176d51"},"extra_attributes":{"createUserId":"787","createTimestamp":1694065883319}},{"x":877.4609138612641,"y":863.5908472146573,"attributes":{"id":"87a98f615ee245c691f923e07a1e35f8"},"extra_attributes":{"createUserId":"787","createTimestamp":1694065883319}},{"x":813.6269699267534,"y":722.3926476960894,"attributes":{"id":"f21de8a687e1444a9a9cf57553e2cf02"},"extra_attributes":{"createUserId":"787","createTimestamp":1694065883319}},{"x":945.3268154203893,"y":652.2202144329418,"attributes":{"id":"27d2e192bf534852b883bbfc43fb3534"},"extra_attributes":{"createUserId":"787","createTimestamp":1694065883319}}]}]},{"type":"roadmark_other","attributes":{"id":"10"},"extra_attributes":{"createUserId":"787","createTimestamp":1694065920825},"objects":[{"type":"roadmark_other_fisheye_front_left_rear_right_bev_box","geometry":"polygon","sensor":"fisheye_front_left_rear_right_bev","attributes":{"id":"10","position":{"x":1392.3881118945776,"y":657.3425456589182},"dimension":{"width":326.24851314785906,"height":137.85061301273709}},"extra_attributes":{"createUserId":"787","createTimestamp":1694065920826,"updateUserId":"787","updateTimestamp":1694065920829,"generateMode":1,"isLeave":false},"points":[{"x":1719.6366250424367,"y":796.1931586716553,"attributes":{"id":"423007811b7c4373a160a9cacb58499b"},"extra_attributes":{"createUserId":"787","createTimestamp":1694065920826}},{"x":1677.987731069611,"y":778.3392220494683,"attributes":{"id":"128abbee7728419ea6e37030b0c492f7"},"extra_attributes":{"createUserId":"787","createTimestamp":1694065920826}},{"x":1620.5067494166412,"y":754.5156162237497,"attributes":{"id":"336b10e1e152426db17151a983621a7c"},"extra_attributes":{"createUserId":"787","createTimestamp":1694065920826}},{"x":1563.2442887025013,"y":734.1337935994582,"attributes":{"id":"573067997b944117999c5b5b62758dee"},"extra_attributes":{"createUserId":"787","createTimestamp":1694065920826}},{"x":1503.0219627817287,"y":712.375437885969,"attributes":{"id":"7e0ba8b44f8b4beaa799515ec5ce799e"},"extra_attributes":{"createUserId":"787","createTimestamp":1694065920826}},{"x":1457.692173468006,"y":689.0146931893419,"attributes":{"id":"2f18bfd8c0ae4671b4600fe0eaeeae89"},"extra_attributes":{"createUserId":"787","createTimestamp":1694065920826}},{"x":1419.2470405700133,"y":671.6185498138777,"attributes":{"id":"02a865d8faaf4f14bc03ea38bc7ab674"},"extra_attributes":{"createUserId":"787","createTimestamp":1694065920826}},{"x":1393.3881118945776,"y":660.4026152691706,"attributes":{"id":"0fcb7bbb52f54af1a0d3664bf45e3c44"},"extra_attributes":{"createUserId":"787","createTimestamp":1694065920826}},{"x":1396.820713046184,"y":658.3425456589182,"attributes":{"id":"9888853bf7d9482aa76cedad96c7e0a2"},"extra_attributes":{"createUserId":"787","createTimestamp":1694065920826}},{"x":1457.692173468006,"y":674.1364126708528,"attributes":{"id":"e22639e2b7ff4bffa7d98785b147be70"},"extra_attributes":{"createUserId":"787","createTimestamp":1694065920826}},{"x":1569.9102550132056,"y":707.7942394501039,"attributes":{"id":"a3dea99d292f44e89f12c4dc18377f3a"},"extra_attributes":{"createUserId":"787","createTimestamp":1694065920826}},{"x":1698.7417971899172,"y":780.1095855886991,"attributes":{"id":"843b430df35e432da6362ebe9e935202"},"extra_attributes":{"createUserId":"787","createTimestamp":1694065920826}}]}]}]}],"qualityCheckResult":{"generated":[]},"workload":{"bundles":[{"keyFrame":true,"invalid":false,"count":9,"groupMap":{"0":{"groupId":"0","type":"lane","count":1,"geometryMap":{"polygon":{"type":"polygon","count":1,"sensorMap":{"fisheye_front_left_rear_right_bev":{"sensorId":"fisheye_front_left_rear_right_bev","type":"fisheye_front_left_rear_right_bev","count":1,"objectCountByType":{"lane_fisheye_front_left_rear_right_bev_box":{"type":"lane_fisheye_front_left_rear_right_bev_box","count":1,"objectCountByGenerateMode":{"1":{"generateMode":1,"count":1,"objectCountByCheckResult":{"qualified":{"checkResult":"qualified","count":1,"detectionCount":0,"noneDetectionCount":0}}}}}}}}}}},"3":{"groupId":"3","type":"ignore","count":1,"geometryMap":{"polygon":{"type":"polygon","count":1,"sensorMap":{"fisheye_front_left_rear_right_bev":{"sensorId":"fisheye_front_left_rear_right_bev","type":"fisheye_front_left_rear_right_bev","count":1,"objectCountByType":{"ignore_fisheye_front_left_rear_right_bev_box":{"type":"ignore_fisheye_front_left_rear_right_bev_box","count":1,"objectCountByGenerateMode":{"1":{"generateMode":1,"count":1,"objectCountByCheckResult":{"qualified":{"checkResult":"qualified","count":1,"detectionCount":0,"noneDetectionCount":0}}}}}}}}}}},"4":{"groupId":"4","type":"ignore","count":1,"geometryMap":{"polygon":{"type":"polygon","count":1,"sensorMap":{"fisheye_front_left_rear_right_bev":{"sensorId":"fisheye_front_left_rear_right_bev","type":"fisheye_front_left_rear_right_bev","count":1,"objectCountByType":{"ignore_fisheye_front_left_rear_right_bev_box":{"type":"ignore_fisheye_front_left_rear_right_bev_box","count":1,"objectCountByGenerateMode":{"1":{"generateMode":1,"count":1,"objectCountByCheckResult":{"qualified":{"checkResult":"qualified","count":1,"detectionCount":0,"noneDetectionCount":0}}}}}}}}}}},"5":{"groupId":"5","type":"ignore","count":1,"geometryMap":{"polygon":{"type":"polygon","count":1,"sensorMap":{"fisheye_front_left_rear_right_bev":{"sensorId":"fisheye_front_left_rear_right_bev","type":"fisheye_front_left_rear_right_bev","count":1,"objectCountByType":{"ignore_fisheye_front_left_rear_right_bev_box":{"type":"ignore_fisheye_front_left_rear_right_bev_box","count":1,"objectCountByGenerateMode":{"1":{"generateMode":1,"count":1,"objectCountByCheckResult":{"qualified":{"checkResult":"qualified","count":1,"detectionCount":0,"noneDetectionCount":0}}}}}}}}}}},"6":{"groupId":"6","type":"stop_line","count":1,"geometryMap":{"polygon":{"type":"polygon","count":1,"sensorMap":{"fisheye_front_left_rear_right_bev":{"sensorId":"fisheye_front_left_rear_right_bev","type":"fisheye_front_left_rear_right_bev","count":1,"objectCountByType":{"stop_line_fisheye_front_left_rear_right_bev_box":{"type":"stop_line_fisheye_front_left_rear_right_bev_box","count":1,"objectCountByGenerateMode":{"1":{"generateMode":1,"count":1,"objectCountByCheckResult":{"qualified":{"checkResult":"qualified","count":1,"detectionCount":0,"noneDetectionCount":0}}}}}}}}}}},"7":{"groupId":"7","type":"lane","count":1,"geometryMap":{"polygon":{"type":"polygon","count":1,"sensorMap":{"fisheye_front_left_rear_right_bev":{"sensorId":"fisheye_front_left_rear_right_bev","type":"fisheye_front_left_rear_right_bev","count":1,"objectCountByType":{"lane_fisheye_front_left_rear_right_bev_box":{"type":"lane_fisheye_front_left_rear_right_bev_box","count":1,"objectCountByGenerateMode":{"1":{"generateMode":1,"count":1,"objectCountByCheckResult":{"qualified":{"checkResult":"qualified","count":1,"detectionCount":0,"noneDetectionCount":0}}}}}}}}}}},"8":{"groupId":"8","type":"lane","count":1,"geometryMap":{"polygon":{"type":"polygon","count":1,"sensorMap":{"fisheye_front_left_rear_right_bev":{"sensorId":"fisheye_front_left_rear_right_bev","type":"fisheye_front_left_rear_right_bev","count":1,"objectCountByType":{"lane_fisheye_front_left_rear_right_bev_box":{"type":"lane_fisheye_front_left_rear_right_bev_box","count":1,"objectCountByGenerateMode":{"1":{"generateMode":1,"count":1,"objectCountByCheckResult":{"qualified":{"checkResult":"qualified","count":1,"detectionCount":0,"noneDetectionCount":0}}}}}}}}}}},"9":{"groupId":"9","type":"roadmark_other","count":1,"geometryMap":{"polygon":{"type":"polygon","count":1,"sensorMap":{"fisheye_front_left_rear_right_bev":{"sensorId":"fisheye_front_left_rear_right_bev","type":"fisheye_front_left_rear_right_bev","count":1,"objectCountByType":{"roadmark_other_fisheye_front_left_rear_right_bev_box":{"type":"roadmark_other_fisheye_front_left_rear_right_bev_box","count":1,"objectCountByGenerateMode":{"1":{"generateMode":1,"count":1,"objectCountByCheckResult":{"qualified":{"checkResult":"qualified","count":1,"detectionCount":0,"noneDetectionCount":0}}}}}}}}}}},"10":{"groupId":"10","type":"roadmark_other","count":1,"geometryMap":{"polygon":{"type":"polygon","count":1,"sensorMap":{"fisheye_front_left_rear_right_bev":{"sensorId":"fisheye_front_left_rear_right_bev","type":"fisheye_front_left_rear_right_bev","count":1,"objectCountByType":{"roadmark_other_fisheye_front_left_rear_right_bev_box":{"type":"roadmark_other_fisheye_front_left_rear_right_bev_box","count":1,"objectCountByGenerateMode":{"1":{"generateMode":1,"count":1,"objectCountByCheckResult":{"qualified":{"checkResult":"qualified","count":1,"detectionCount":0,"noneDetectionCount":0}}}}}}}}}}}}}]}}