{"attributes":{},"extra_attributes":{"version":39,"type":"ap_lane_2d_dmyscdx","taskId":"2784","dataId":"498"},"bundles":[{"attributes":{"id":"0","invalid":false},"extra_attributes":{"keyFrame":true,"bundleFileName":"right_fisheye_camera_1691978356775481312.json"},"groups":[{"type":"stop_line","attributes":{"id":"18"},"extra_attributes":{"createUserId":"787","createTimestamp":1693967881158},"objects":[{"type":"stop_line_fisheye_front_left_rear_right_bev_box","geometry":"polygon","sensor":"fisheye_front_left_rear_right_bev","attributes":{"id":"0","position":{"x":260.29542858949833,"y":506.9645381382304},"dimension":{"width":492.011368001685,"height":503.3756903868313}},"extra_attributes":{"createUserId":"787","createTimestamp":1692838164927,"updateUserId":"787","updateTimestamp":1693967881161,"generateMode":1,"isLeave":false},"points":[{"x":288.39734376277863,"y":1011.3402285250618,"attributes":{"id":"d54b2bd8c3a44ead957015de543b02ea"},"extra_attributes":{"createUserId":"787","createTimestamp":1692838164927,"updateUserId":"787","updateTimestamp":1693967857785}},{"x":349.32793960585025,"y":907.5048865029953,"attributes":{"id":"64b95f988fe949b3a62b668c24984b54"},"extra_attributes":{"createUserId":"787","createTimestamp":1692838164927,"updateUserId":"787","updateTimestamp":1693967857785}},{"x":429.44038969581504,"y":799.1549643930127,"attributes":{"id":"60fbfe124a364ecbaa1a1abe41a1b4a8"},"extra_attributes":{"createUserId":"787","createTimestamp":1692838164927,"updateUserId":"787","updateTimestamp":1693967857785}},{"x":490.86545715098026,"y":730.3911022646105,"attributes":{"id":"c795042e3d6a4ba48ed8bc4063d3740a"},"extra_attributes":{"createUserId":"787","createTimestamp":1692838164927,"updateUserId":"787","updateTimestamp":1693967857785}},{"x":647.210852616423,"y":588.0983452829428,"attributes":{"id":"da27bbb1c4fe4fecb5f3dc242064b3ae"},"extra_attributes":{"createUserId":"787","createTimestamp":1692838164927,"updateUserId":"787","updateTimestamp":1693967857785}},{"x":729.4624515471195,"y":524.2448831196364,"attributes":{"id":"9b3d040b29174d90a062cb34b7092d78"},"extra_attributes":{"createUserId":"787","createTimestamp":1692838164927,"updateUserId":"787","updateTimestamp":1693967857785}},{"x":753.3067965911833,"y":507.96453813823047,"attributes":{"id":"9336507714cd4bafbce607ba0d59d498"},"extra_attributes":{"createUserId":"787","createTimestamp":1692838164927,"updateUserId":"787","updateTimestamp":1693967857785}},{"x":717.2491266225559,"y":512.2913756479718,"attributes":{"id":"f6c404146cfb40cca2dab5dd734c26f1"},"extra_attributes":{"createUserId":"787","createTimestamp":1692838164927,"updateUserId":"787","updateTimestamp":1693967857785}},{"x":503.7735548350844,"y":677.3586559700557,"attributes":{"id":"7a242088c2c34b24a82b410731a07344"},"extra_attributes":{"createUserId":"787","createTimestamp":1692838164927,"updateUserId":"787","updateTimestamp":1693967857785}},{"x":420.8153655426589,"y":756.6197931494573,"attributes":{"id":"bd09819df6b648b498ce6b72186d541e"},"extra_attributes":{"createUserId":"787","createTimestamp":1692838164927,"updateUserId":"787","updateTimestamp":1693967857785}},{"x":337.11812805776765,"y":861.976922922875,"attributes":{"id":"1ccfb9ae55334cee8203e089e63cd0a4"},"extra_attributes":{"createUserId":"787","createTimestamp":1692838164927,"updateUserId":"787","updateTimestamp":1693967857785}},{"x":294.62499977461573,"y":924.4018102556472,"attributes":{"id":"2ede1da54f9a4c8baf204cc6457ebe5e"},"extra_attributes":{"createUserId":"787","createTimestamp":1693967829461,"updateUserId":"787","updateTimestamp":1693967857785}},{"x":261.29542858949833,"y":984.2527499260441,"attributes":{"id":"685206d169cc4b5da28a45d92a714927"},"extra_attributes":{"createUserId":"787","createTimestamp":1692838164927,"updateUserId":"787","updateTimestamp":1693967857785}}]}]},{"type":"lane","attributes":{"id":"1"},"extra_attributes":{"createUserId":"787","createTimestamp":1692838286541},"objects":[{"type":"lane_fisheye_front_left_rear_right_bev_box","geometry":"polygon","sensor":"fisheye_front_left_rear_right_bev","attributes":{"id":"1","position":{"x":429.6112793770243,"y":687.7818514464914},"dimension":{"width":1403.3353215600978,"height":120.33632557915655}},"extra_attributes":{"createUserId":"787","createTimestamp":1692838286542,"updateUserId":"787","updateTimestamp":1692838286558,"generateMode":1,"isLeave":false},"points":[{"x":430.6112793770243,"y":802.659591678904,"attributes":{"id":"729cfcc54d80485baf330c78549de8ed"},"extra_attributes":{"createUserId":"787","createTimestamp":1692838286543}},{"x":653.4848366879992,"y":808.7234290410224,"attributes":{"id":"ff7ffc6a224749bdad365d8aead3f7fd"},"extra_attributes":{"createUserId":"787","createTimestamp":1692838286543}},{"x":787.3214730494431,"y":809.1181770256479,"attributes":{"id":"1ffe94921a694f1e8ebae6fc8576efa5"},"extra_attributes":{"createUserId":"787","createTimestamp":1692838286543}},{"x":951.1560186129984,"y":804.3811999866441,"attributes":{"id":"e2d695363c354ce9ad68fcd804131923"},"extra_attributes":{"createUserId":"787","createTimestamp":1692838286543}},{"x":1144.177732721153,"y":795.3019938148325,"attributes":{"id":"617a1aa7c1634c04850cbf1fc5225cbe"},"extra_attributes":{"createUserId":"787","createTimestamp":1692838286543}},{"x":1303.2664669932722,"y":784.2490477042077,"attributes":{"id":"9606f4e31ceb4a50848feac818f4f010"},"extra_attributes":{"createUserId":"787","createTimestamp":1692838286543}},{"x":1427.8549918123815,"y":772.7690234430557,"attributes":{"id":"93f17d594d3e402caf6891d23db7960a"},"extra_attributes":{"createUserId":"787","createTimestamp":1692838286543}},{"x":1543.0377107919298,"y":756.801369318689,"attributes":{"id":"7419063eb9474631a5a2202af2c22ad8"},"extra_attributes":{"createUserId":"787","createTimestamp":1692838286543}},{"x":1612.3368832744065,"y":743.8913513874764,"attributes":{"id":"bd228c604a31495588e66f1f22ff4b07"},"extra_attributes":{"createUserId":"787","createTimestamp":1692838286544}},{"x":1678.2485486244886,"y":731.3210700490617,"attributes":{"id":"812f0d6122074ab9b8417e6979e11b92"},"extra_attributes":{"createUserId":"787","createTimestamp":1692838286544}},{"x":1752.3654603817479,"y":714.8047999845757,"attributes":{"id":"602fdbf37ecf4d8eb30265d1fbf6d4d7"},"extra_attributes":{"createUserId":"787","createTimestamp":1692838286544}},{"x":1802.961234563677,"y":701.9395214270536,"attributes":{"id":"1f0670a0c9a74bf4ae2f252b8fc2b2d1"},"extra_attributes":{"createUserId":"787","createTimestamp":1692838286544}},{"x":1833.946600937122,"y":691.1209927763691,"attributes":{"id":"bdbbb628805348e7939f4cebce4bfe9f"},"extra_attributes":{"createUserId":"787","createTimestamp":1692838286544}},{"x":1831.9003974973662,"y":688.7818514464914,"attributes":{"id":"0d96b0ccd2a24bc4807cae4510d6f5a3"},"extra_attributes":{"createUserId":"787","createTimestamp":1692838286544}},{"x":1785.1300331600908,"y":698.7232020984717,"attributes":{"id":"6124408cd7b841b38da644beeed0b59f"},"extra_attributes":{"createUserId":"787","createTimestamp":1692838286544}},{"x":1717.297113118983,"y":711.2960877806236,"attributes":{"id":"6e35b6b4a5dd4ade8643bd552d1f3287"},"extra_attributes":{"createUserId":"787","createTimestamp":1692838286544}},{"x":1637.1783254566026,"y":720.3602622580263,"attributes":{"id":"bae9bff2c6b54d70a8d51dcffad1caf4"},"extra_attributes":{"createUserId":"787","createTimestamp":1692838286544}},{"x":1513.1537481369849,"y":735.6625343368321,"attributes":{"id":"5ba5d8fe3c624314a1b5629d116ff5bc"},"extra_attributes":{"createUserId":"787","createTimestamp":1692838286544}},{"x":1406.7091068938953,"y":746.2316589270891,"attributes":{"id":"eb080092c36b43a6ab5a731687824261"},"extra_attributes":{"createUserId":"787","createTimestamp":1692838286544}},{"x":1212.1602995139617,"y":759.0035661980736,"attributes":{"id":"79e02d0899f74b7a9d514c40bdc61ec6"},"extra_attributes":{"createUserId":"787","createTimestamp":1692838286544}},{"x":1048.9170794287309,"y":765.4860589915285,"attributes":{"id":"ed1ce559531f4c9b8efed16f557e2dee"},"extra_attributes":{"createUserId":"787","createTimestamp":1692838286544}},{"x":814.7458110532293,"y":773.7636752699128,"attributes":{"id":"5e1c1370ce7645638ed48f84a6dced72"},"extra_attributes":{"createUserId":"787","createTimestamp":1692838286544}},{"x":684.0368408397733,"y":777.7490506794511,"attributes":{"id":"a789428cc080477fa0a14e4e4d9a53d2"},"extra_attributes":{"createUserId":"787","createTimestamp":1692838286544}},{"x":557.2049993100476,"y":777.7490507794461,"attributes":{"id":"9af81ed516b04355a9a0626c445e114b"},"extra_attributes":{"createUserId":"787","createTimestamp":1692838286544}},{"x":453.28211283647323,"y":776.4908219127365,"attributes":{"id":"742e0ad2fa4c48418fa5c397cb10a4de"},"extra_attributes":{"createUserId":"787","createTimestamp":1692838286544}}]}]},{"type":"lane","attributes":{"id":"2"},"extra_attributes":{"createUserId":"787","createTimestamp":1692838325639},"objects":[{"type":"lane_fisheye_front_left_rear_right_bev_box","geometry":"polygon","sensor":"fisheye_front_left_rear_right_bev","attributes":{"id":"2","position":{"x":734.8788111593099,"y":493.8666911121687},"dimension":{"width":343.2965745133324,"height":26.294515545118315}},"extra_attributes":{"createUserId":"787","createTimestamp":1692838325644,"updateUserId":"787","updateTimestamp":1692838325646,"generateMode":1,"isLeave":false},"points":[{"x":1077.311410877625,"y":500.99274973996637,"attributes":{"id":"30ca6cde91b9441dbb89bd934eae406c"},"extra_attributes":{"createUserId":"787","createTimestamp":1692838325645}},{"x":977.1464826760542,"y":502.0586180142442,"attributes":{"id":"6d85a85e8df144ba8246631e9f21377b"},"extra_attributes":{"createUserId":"787","createTimestamp":1692838325645}},{"x":863.1289580210748,"y":508.4538276599111,"attributes":{"id":"892e8ce635564e4787b9e6c928abbf47"},"extra_attributes":{"createUserId":"787","createTimestamp":1692838325645}},{"x":735.8788111593099,"y":521.161206657287,"attributes":{"id":"0b4990f46c1b440dbdd960f465af54d3"},"extra_attributes":{"createUserId":"787","createTimestamp":1692838325645}},{"x":758.5804049047512,"y":509.80738529273253,"attributes":{"id":"5a980e9948844e26afbb453c5376aabb"},"extra_attributes":{"createUserId":"787","createTimestamp":1692838325645}},{"x":860.1823881721143,"y":502.1814406521661,"attributes":{"id":"fb8dfb61b8bf4595993f9c1921193a85"},"extra_attributes":{"createUserId":"787","createTimestamp":1692838325645}},{"x":957.727466424487,"y":496.35904137116734,"attributes":{"id":"7384a8ad4604477587436ff626000b54"},"extra_attributes":{"createUserId":"787","createTimestamp":1692838325645}},{"x":1079.1753856726423,"y":494.8666911121687,"attributes":{"id":"3ab0bf111035403aa7bfef10e47ca3d4"},"extra_attributes":{"createUserId":"787","createTimestamp":1692838325645}}]}]},{"type":"ignore","attributes":{"id":"17"},"extra_attributes":{"createUserId":"787","createTimestamp":1693550737310},"objects":[{"type":"ignore_fisheye_front_left_rear_right_bev_box","geometry":"polygon","sensor":"fisheye_front_left_rear_right_bev","attributes":{"id":"3","position":{"x":56.387612224424544,"y":568.3793915863257},"dimension":{"width":248.87854882109912,"height":282.0415801242556}},"extra_attributes":{"createUserId":"787","createTimestamp":1692838334135,"updateUserId":"787","updateTimestamp":1693550737318,"generateMode":1,"isLeave":false},"points":[{"x":306.26616104552363,"y":569.3793915863258,"attributes":{"id":"a28a922e30c44d62a11a7c8da77a03c4"},"extra_attributes":{"createUserId":"787","createTimestamp":1692838334135,"updateUserId":"787","updateTimestamp":1693550729640}},{"x":57.387612224424515,"y":851.4209717105814,"attributes":{"id":"51ca8458180841958c7466b87cb2ce71"},"extra_attributes":{"createUserId":"787","createTimestamp":1692838334135,"updateUserId":"787","updateTimestamp":1693550729640}},{"x":78.91685377795028,"y":762.2339209352438,"attributes":{"id":"3339e4a762d34553bb58cfc3140f41ea"},"extra_attributes":{"createUserId":"787","createTimestamp":1692838334135,"updateUserId":"787","updateTimestamp":1693550729640}}]}]},{"type":"ignore","attributes":{"id":"4"},"extra_attributes":{"createUserId":"787","createTimestamp":1692838349229},"objects":[{"type":"ignore_fisheye_front_left_rear_right_bev_box","geometry":"polygon","sensor":"fisheye_front_left_rear_right_bev","attributes":{"id":"4","position":{"x":331.67338675148756,"y":433.40062929501613},"dimension":{"width":438.426529767906,"height":180.25583502469505}},"extra_attributes":{"createUserId":"787","createTimestamp":1692838349230,"updateUserId":"787","updateTimestamp":1692838349232,"generateMode":1,"isLeave":false},"points":[{"x":571.574840220144,"y":549.9845246863467,"attributes":{"id":"be66c8b1cfd14b95a91653e77165d88a"},"extra_attributes":{"createUserId":"787","createTimestamp":1692838349231}},{"x":504.6274079621328,"y":569.2485067047957,"attributes":{"id":"1cb0873e9d214c29a36dc01edf870515"},"extra_attributes":{"createUserId":"787","createTimestamp":1692838349231}},{"x":332.67338675148756,"y":614.6564643197112,"attributes":{"id":"3793ac1667184a86ade74f874688ed27"},"extra_attributes":{"createUserId":"787","createTimestamp":1692838349231}},{"x":473.90495617249746,"y":474.3045953281542,"attributes":{"id":"89efd872220d43d1a23216a223961639"},"extra_attributes":{"createUserId":"787","createTimestamp":1692838349231}},{"x":771.0999165193936,"y":434.40062929501613,"attributes":{"id":"4d3047b6590a4f27aa79559ae6453baf"},"extra_attributes":{"createUserId":"787","createTimestamp":1692838349231}}]}]},{"type":"crossing","attributes":{"id":"5"},"extra_attributes":{"createUserId":"787","createTimestamp":1692838364337},"objects":[{"type":"crossing_fisheye_front_left_rear_right_bev_box","geometry":"polygon","sensor":"fisheye_front_left_rear_right_bev","attributes":{"id":"5","position":{"x":315.336072347418,"y":579.9933050478635},"dimension":{"width":165.57112772665272,"height":57.936130468246915}},"extra_attributes":{"createUserId":"787","createTimestamp":1692838364338,"updateUserId":"787","updateTimestamp":1692838364344,"generateMode":1,"isLeave":false},"points":[{"x":460.3522925809075,"y":593.744373067365,"attributes":{"id":"66e9fe3eb15c4876915c66173f921aa0"},"extra_attributes":{"createUserId":"787","createTimestamp":1692838364340}},{"x":316.336072347418,"y":638.9294355161104,"attributes":{"id":"d0fbbc4b7ba74aa49962d1eb5e7abd86"},"extra_attributes":{"createUserId":"787","createTimestamp":1692838364340}},{"x":325.1668893358829,"y":625.3399431843067,"attributes":{"id":"a123a39367f84b55b50aacd2a674dcc0"},"extra_attributes":{"createUserId":"787","createTimestamp":1692838364340}},{"x":481.9072000740707,"y":580.9933050478635,"attributes":{"id":"d30eeaee348241e9b4150aa48c4584a5"},"extra_attributes":{"createUserId":"787","createTimestamp":1692838364340}}]}]},{"type":"crossing","attributes":{"id":"6"},"extra_attributes":{"createUserId":"787","createTimestamp":1692838377217},"objects":[{"type":"crossing_fisheye_front_left_rear_right_bev_box","geometry":"polygon","sensor":"fisheye_front_left_rear_right_bev","attributes":{"id":"6","position":{"x":256.9155050957047,"y":625.556861077652},"dimension":{"width":152.5014164546442,"height":56.73613048528023}},"extra_attributes":{"createUserId":"787","createTimestamp":1692838377218,"updateUserId":"787","updateTimestamp":1692838377220,"generateMode":1,"isLeave":false},"points":[{"x":387.6605854646893,"y":645.5821503421771,"attributes":{"id":"c164762555d64b609ea2dea8b9a29a1b"},"extra_attributes":{"createUserId":"787","createTimestamp":1692838377218}},{"x":257.9155050957047,"y":683.2929915629322,"attributes":{"id":"bc9afb25b48e499fa7fca0e139d996b3"},"extra_attributes":{"createUserId":"787","createTimestamp":1692838377218}},{"x":289.5026581698292,"y":662.2292784486366,"attributes":{"id":"12a5262b730d4bef81c1c8b6d7800b2c"},"extra_attributes":{"createUserId":"787","createTimestamp":1692838377218}},{"x":410.4169215503489,"y":626.556861077652,"attributes":{"id":"89a0ebcdcc164934b0b54e7d369352ad"},"extra_attributes":{"createUserId":"787","createTimestamp":1692838377218}}]}]},{"type":"crossing","attributes":{"id":"7"},"extra_attributes":{"createUserId":"787","createTimestamp":1692838384386},"objects":[{"type":"crossing_fisheye_front_left_rear_right_bev_box","geometry":"polygon","sensor":"fisheye_front_left_rear_right_bev","attributes":{"id":"7","position":{"x":210.11341494602217,"y":677.7926654061571},"dimension":{"width":135.75716033427747,"height":46.18552337741596}},"extra_attributes":{"createUserId":"787","createTimestamp":1692838384393,"updateUserId":"787","updateTimestamp":1692838384395,"generateMode":1,"isLeave":false},"points":[{"x":313.7205710126272,"y":708.3987701352698,"attributes":{"id":"f0fa1d331338415881ee122b347ba8c4"},"extra_attributes":{"createUserId":"787","createTimestamp":1692838384393}},{"x":211.11341494602217,"y":724.978188783573,"attributes":{"id":"4f208beddb9948d6807d6eaef38a00e5"},"extra_attributes":{"createUserId":"787","createTimestamp":1692838384394}},{"x":228.87234580370378,"y":704.8460375677763,"attributes":{"id":"1cb66c2c35394b47888a4b5f77b1a102"},"extra_attributes":{"createUserId":"787","createTimestamp":1692838384394}},{"x":346.87057528029965,"y":678.7926654061571,"attributes":{"id":"9c606b0960894fa4a6b0cb5713ce56e8"},"extra_attributes":{"createUserId":"787","createTimestamp":1692838384394}}]}]},{"type":"crossing","attributes":{"id":"8"},"extra_attributes":{"createUserId":"787","createTimestamp":1692838392529},"objects":[{"type":"crossing_fisheye_front_left_rear_right_bev_box","geometry":"polygon","sensor":"fisheye_front_left_rear_right_bev","attributes":{"id":"8","position":{"x":166.68712979443856,"y":748.4525707635089},"dimension":{"width":101.42322734275965,"height":33.55358535966104}},"extra_attributes":{"createUserId":"787","createTimestamp":1692838392531,"updateUserId":"787","updateTimestamp":1692838392537,"generateMode":1,"isLeave":false},"points":[{"x":239.11749613311363,"y":783.00615612317,"attributes":{"id":"7b979e8876f94043aa7c433cc69315a4"},"extra_attributes":{"createUserId":"787","createTimestamp":1692838392532}},{"x":167.68712979443856,"y":771.5584622945797,"attributes":{"id":"55696944770c4982909ca95406c56cf0"},"extra_attributes":{"createUserId":"787","createTimestamp":1692838392532}},{"x":186.23534646801718,"y":751.4263110787831,"attributes":{"id":"d6d48802656a4af597b71643eae2f9d7"},"extra_attributes":{"createUserId":"787","createTimestamp":1692838392532}},{"x":269.1103571371982,"y":749.4525707635089,"attributes":{"id":"4ac945f14cec4bd9a6b0afb8bad955a0"},"extra_attributes":{"createUserId":"787","createTimestamp":1692838392532}}]}]},{"type":"crossing","attributes":{"id":"9"},"extra_attributes":{"createUserId":"787","createTimestamp":1692838401358},"objects":[{"type":"crossing_fisheye_front_left_rear_right_bev_box","geometry":"polygon","sensor":"fisheye_front_left_rear_right_bev","attributes":{"id":"9","position":{"x":126.76204596180762,"y":801.4207855837385},"dimension":{"width":67.86452037113469,"height":69.25860201870955}},"extra_attributes":{"createUserId":"787","createTimestamp":1692838401358,"updateUserId":"787","updateTimestamp":1692838401362,"generateMode":1,"isLeave":false},"points":[{"x":167.6553788826773,"y":871.6793876024481,"attributes":{"id":"19b5aa5d714c44e3bd1d1273ea531ba6"},"extra_attributes":{"createUserId":"787","createTimestamp":1692838401359}},{"x":127.76204596180762,"y":824.4367650333945,"attributes":{"id":"861c0360f63b475cb3ec831764bb704b"},"extra_attributes":{"createUserId":"787","createTimestamp":1692838401359}},{"x":142.8939998283444,"y":802.4207855837385,"attributes":{"id":"c3a51a1b2912404daaba9ccc92d360ad"},"extra_attributes":{"createUserId":"787","createTimestamp":1692838401359}},{"x":195.6265663329423,"y":834.5274222811536,"attributes":{"id":"5d56db06dfe549a6bdbda87c28eb6030"},"extra_attributes":{"createUserId":"787","createTimestamp":1692838401359}}]}]},{"type":"crossing","attributes":{"id":"10"},"extra_attributes":{"createUserId":"787","createTimestamp":1692838410791},"objects":[{"type":"crossing_fisheye_front_left_rear_right_bev_box","geometry":"polygon","sensor":"fisheye_front_left_rear_right_bev","attributes":{"id":"10","position":{"x":90.43177515242019,"y":855.964947039409},"dimension":{"width":30.782146819981563,"height":50.52775207101911}},"extra_attributes":{"createUserId":"787","createTimestamp":1692838410792,"updateUserId":"787","updateTimestamp":1692838410799,"generateMode":1,"isLeave":false},"points":[{"x":122.21392197240175,"y":907.4926991104281,"attributes":{"id":"e50cd2fbaa934e65a5bdb20a49ceedb0"},"extra_attributes":{"createUserId":"787","createTimestamp":1692838410794}},{"x":106.03356274651401,"y":856.964947039409,"attributes":{"id":"3c6392016a864261abe472e9ff744e72"},"extra_attributes":{"createUserId":"787","createTimestamp":1692838410794}},{"x":91.43177515242019,"y":876.7023501921509,"attributes":{"id":"d9aca843bb54451db4982fa77490bc3d"},"extra_attributes":{"createUserId":"787","createTimestamp":1692838410794}},{"x":96.16749004780195,"y":902.7557223537701,"attributes":{"id":"463ac342cef14b5e8d92455b767fbdaf"},"extra_attributes":{"createUserId":"787","createTimestamp":1692838410794}}]}]},{"type":"arrow","attributes":{"id":"12"},"extra_attributes":{"createUserId":"787","createTimestamp":1693201785562},"objects":[{"type":"arrow_fisheye_front_left_rear_right_bev_box","geometry":"polygon","sensor":"fisheye_front_left_rear_right_bev","attributes":{"id":"12","position":{"x":1591.8492269561984,"y":882.1076940212462},"dimension":{"width":104.84043233740567,"height":133.56763333858623}},"extra_attributes":{"createUserId":"787","createTimestamp":1693201785562,"updateUserId":"787","updateTimestamp":1693201785564,"generateMode":1,"isLeave":false},"points":[{"x":1592.8492269561984,"y":1016.6753273598324,"attributes":{"id":"621cd4a14f3844988e23564e573aa962"},"extra_attributes":{"createUserId":"787","createTimestamp":1693201785563}},{"x":1636.7567584479325,"y":947.2022294823798,"attributes":{"id":"6b63ff9412a24aac9f576ad23979a8dd"},"extra_attributes":{"createUserId":"787","createTimestamp":1693201785563}},{"x":1671.7035692270676,"y":883.1076940212462,"attributes":{"id":"629c5b1f651b4eaea81566a211719fa5"},"extra_attributes":{"createUserId":"787","createTimestamp":1693201785563}},{"x":1697.689659293604,"y":923.8951256783313,"attributes":{"id":"14261c8bab894ca6a06ab8309f1da28c"},"extra_attributes":{"createUserId":"787","createTimestamp":1693201785563}}]}]},{"type":"lane","attributes":{"id":"14"},"extra_attributes":{"createUserId":"787","createTimestamp":1693550700302},"objects":[{"type":"lane_fisheye_front_left_rear_right_bev_box","geometry":"polygon","sensor":"fisheye_front_left_rear_right_bev","attributes":{"id":"14","position":{"x":1090.5975493337228,"y":438.57910152557986},"dimension":{"width":15.232164166070106,"height":3.5979080296630173}},"extra_attributes":{"createUserId":"787","createTimestamp":1693550700303,"updateUserId":"787","updateTimestamp":1693550700309,"generateMode":1,"isLeave":false},"points":[{"x":1091.5975493337228,"y":443.1770095552429,"attributes":{"id":"1f2a17ddb92e49c98953e734a2f71734"},"extra_attributes":{"createUserId":"787","createTimestamp":1693550700305}},{"x":1106.4065978285132,"y":442.330442960028,"attributes":{"id":"7cfe5090b4624aacb42ba9d01418ae64"},"extra_attributes":{"createUserId":"787","createTimestamp":1693550700305}},{"x":1106.829713499793,"y":439.57910152557986,"attributes":{"id":"3f37940e96824522a44165f520242f23"},"extra_attributes":{"createUserId":"787","createTimestamp":1693550700305}},{"x":1091.5975493337228,"y":439.57910152557986,"attributes":{"id":"aa31e9f8199f4ec7944accc2a4bef398"},"extra_attributes":{"createUserId":"787","createTimestamp":1693550700305}}]}]},{"type":"lane","attributes":{"id":"15"},"extra_attributes":{"createUserId":"787","createTimestamp":1693550704972},"objects":[{"type":"lane_fisheye_front_left_rear_right_bev_box","geometry":"polygon","sensor":"fisheye_front_left_rear_right_bev","attributes":{"id":"15","position":{"x":1088.9183186032267,"y":447.21895588945125},"dimension":{"width":7.208309322043988,"height":3.1352891513203076}},"extra_attributes":{"createUserId":"787","createTimestamp":1693550704973,"updateUserId":"787","updateTimestamp":1693550704976,"generateMode":1,"isLeave":false},"points":[{"x":1089.9183186032267,"y":451.35424504077156,"attributes":{"id":"e0e6ddafe03e4593a0ce307e5881022d"},"extra_attributes":{"createUserId":"787","createTimestamp":1693550704974}},{"x":1097.1266279252707,"y":451.19748058320556,"attributes":{"id":"28c16dbab6b0438ea669817bffa812bb"},"extra_attributes":{"createUserId":"787","createTimestamp":1693550704974}},{"x":1096.499818419006,"y":450.10012938024346,"attributes":{"id":"05f31d318a0f460794bd85c2c0e82271"},"extra_attributes":{"createUserId":"787","createTimestamp":1693550704974}},{"x":1090.2317233563592,"y":448.21895588945125,"attributes":{"id":"8ceb9ba7ace342d0b5ed39b4551823e3"},"extra_attributes":{"createUserId":"787","createTimestamp":1693550704974}}]}]},{"type":"lane","attributes":{"id":"16"},"extra_attributes":{"createUserId":"787","createTimestamp":1693550712421},"objects":[{"type":"lane_fisheye_front_left_rear_right_bev_box","geometry":"polygon","sensor":"fisheye_front_left_rear_right_bev","attributes":{"id":"16","position":{"x":1072.4267960082784,"y":462.2694530501884},"dimension":{"width":16.48201842349522,"height":5.805826805564209}},"extra_attributes":{"createUserId":"787","createTimestamp":1693550712422,"updateUserId":"787","updateTimestamp":1693550712425,"generateMode":1,"isLeave":false},"points":[{"x":1073.4267960082784,"y":469.0752798557526,"attributes":{"id":"742783332d96433aafc140f400a3bd93"},"extra_attributes":{"createUserId":"787","createTimestamp":1693550712423}},{"x":1089.560602774939,"y":467.33353181408336,"attributes":{"id":"71a9664ba39146e09905b820804c2e92"},"extra_attributes":{"createUserId":"787","createTimestamp":1693550712423}},{"x":1089.9088144317736,"y":465.127317627969,"attributes":{"id":"e2c2c75908de403a98c6c7a244597655"},"extra_attributes":{"createUserId":"787","createTimestamp":1693550712423}},{"x":1080.2749585926883,"y":463.2694530501884,"attributes":{"id":"4f8aa8d585eb44e297189aa81e5df7be"},"extra_attributes":{"createUserId":"787","createTimestamp":1693550712423}}]}]}]}],"qualityCheckResult":{"generated":[]},"workload":{"bundles":[{"keyFrame":true,"invalid":false,"count":15,"groupMap":{"1":{"groupId":"1","type":"lane","count":1,"geometryMap":{"polygon":{"type":"polygon","count":1,"sensorMap":{"fisheye_front_left_rear_right_bev":{"sensorId":"fisheye_front_left_rear_right_bev","type":"fisheye_front_left_rear_right_bev","count":1,"objectCountByType":{"lane_fisheye_front_left_rear_right_bev_box":{"type":"lane_fisheye_front_left_rear_right_bev_box","count":1,"objectCountByGenerateMode":{"1":{"generateMode":1,"count":1,"objectCountByCheckResult":{"qualified":{"checkResult":"qualified","count":1,"detectionCount":0,"noneDetectionCount":0}}}}}}}}}}},"2":{"groupId":"2","type":"lane","count":1,"geometryMap":{"polygon":{"type":"polygon","count":1,"sensorMap":{"fisheye_front_left_rear_right_bev":{"sensorId":"fisheye_front_left_rear_right_bev","type":"fisheye_front_left_rear_right_bev","count":1,"objectCountByType":{"lane_fisheye_front_left_rear_right_bev_box":{"type":"lane_fisheye_front_left_rear_right_bev_box","count":1,"objectCountByGenerateMode":{"1":{"generateMode":1,"count":1,"objectCountByCheckResult":{"qualified":{"checkResult":"qualified","count":1,"detectionCount":0,"noneDetectionCount":0}}}}}}}}}}},"4":{"groupId":"4","type":"ignore","count":1,"geometryMap":{"polygon":{"type":"polygon","count":1,"sensorMap":{"fisheye_front_left_rear_right_bev":{"sensorId":"fisheye_front_left_rear_right_bev","type":"fisheye_front_left_rear_right_bev","count":1,"objectCountByType":{"ignore_fisheye_front_left_rear_right_bev_box":{"type":"ignore_fisheye_front_left_rear_right_bev_box","count":1,"objectCountByGenerateMode":{"1":{"generateMode":1,"count":1,"objectCountByCheckResult":{"qualified":{"checkResult":"qualified","count":1,"detectionCount":0,"noneDetectionCount":0}}}}}}}}}}},"5":{"groupId":"5","type":"crossing","count":1,"geometryMap":{"polygon":{"type":"polygon","count":1,"sensorMap":{"fisheye_front_left_rear_right_bev":{"sensorId":"fisheye_front_left_rear_right_bev","type":"fisheye_front_left_rear_right_bev","count":1,"objectCountByType":{"crossing_fisheye_front_left_rear_right_bev_box":{"type":"crossing_fisheye_front_left_rear_right_bev_box","count":1,"objectCountByGenerateMode":{"1":{"generateMode":1,"count":1,"objectCountByCheckResult":{"qualified":{"checkResult":"qualified","count":1,"detectionCount":0,"noneDetectionCount":0}}}}}}}}}}},"6":{"groupId":"6","type":"crossing","count":1,"geometryMap":{"polygon":{"type":"polygon","count":1,"sensorMap":{"fisheye_front_left_rear_right_bev":{"sensorId":"fisheye_front_left_rear_right_bev","type":"fisheye_front_left_rear_right_bev","count":1,"objectCountByType":{"crossing_fisheye_front_left_rear_right_bev_box":{"type":"crossing_fisheye_front_left_rear_right_bev_box","count":1,"objectCountByGenerateMode":{"1":{"generateMode":1,"count":1,"objectCountByCheckResult":{"qualified":{"checkResult":"qualified","count":1,"detectionCount":0,"noneDetectionCount":0}}}}}}}}}}},"7":{"groupId":"7","type":"crossing","count":1,"geometryMap":{"polygon":{"type":"polygon","count":1,"sensorMap":{"fisheye_front_left_rear_right_bev":{"sensorId":"fisheye_front_left_rear_right_bev","type":"fisheye_front_left_rear_right_bev","count":1,"objectCountByType":{"crossing_fisheye_front_left_rear_right_bev_box":{"type":"crossing_fisheye_front_left_rear_right_bev_box","count":1,"objectCountByGenerateMode":{"1":{"generateMode":1,"count":1,"objectCountByCheckResult":{"qualified":{"checkResult":"qualified","count":1,"detectionCount":0,"noneDetectionCount":0}}}}}}}}}}},"8":{"groupId":"8","type":"crossing","count":1,"geometryMap":{"polygon":{"type":"polygon","count":1,"sensorMap":{"fisheye_front_left_rear_right_bev":{"sensorId":"fisheye_front_left_rear_right_bev","type":"fisheye_front_left_rear_right_bev","count":1,"objectCountByType":{"crossing_fisheye_front_left_rear_right_bev_box":{"type":"crossing_fisheye_front_left_rear_right_bev_box","count":1,"objectCountByGenerateMode":{"1":{"generateMode":1,"count":1,"objectCountByCheckResult":{"qualified":{"checkResult":"qualified","count":1,"detectionCount":0,"noneDetectionCount":0}}}}}}}}}}},"9":{"groupId":"9","type":"crossing","count":1,"geometryMap":{"polygon":{"type":"polygon","count":1,"sensorMap":{"fisheye_front_left_rear_right_bev":{"sensorId":"fisheye_front_left_rear_right_bev","type":"fisheye_front_left_rear_right_bev","count":1,"objectCountByType":{"crossing_fisheye_front_left_rear_right_bev_box":{"type":"crossing_fisheye_front_left_rear_right_bev_box","count":1,"objectCountByGenerateMode":{"1":{"generateMode":1,"count":1,"objectCountByCheckResult":{"qualified":{"checkResult":"qualified","count":1,"detectionCount":0,"noneDetectionCount":0}}}}}}}}}}},"10":{"groupId":"10","type":"crossing","count":1,"geometryMap":{"polygon":{"type":"polygon","count":1,"sensorMap":{"fisheye_front_left_rear_right_bev":{"sensorId":"fisheye_front_left_rear_right_bev","type":"fisheye_front_left_rear_right_bev","count":1,"objectCountByType":{"crossing_fisheye_front_left_rear_right_bev_box":{"type":"crossing_fisheye_front_left_rear_right_bev_box","count":1,"objectCountByGenerateMode":{"1":{"generateMode":1,"count":1,"objectCountByCheckResult":{"qualified":{"checkResult":"qualified","count":1,"detectionCount":0,"noneDetectionCount":0}}}}}}}}}}},"12":{"groupId":"12","type":"arrow","count":1,"geometryMap":{"polygon":{"type":"polygon","count":1,"sensorMap":{"fisheye_front_left_rear_right_bev":{"sensorId":"fisheye_front_left_rear_right_bev","type":"fisheye_front_left_rear_right_bev","count":1,"objectCountByType":{"arrow_fisheye_front_left_rear_right_bev_box":{"type":"arrow_fisheye_front_left_rear_right_bev_box","count":1,"objectCountByGenerateMode":{"1":{"generateMode":1,"count":1,"objectCountByCheckResult":{"qualified":{"checkResult":"qualified","count":1,"detectionCount":0,"noneDetectionCount":0}}}}}}}}}}},"14":{"groupId":"14","type":"lane","count":1,"geometryMap":{"polygon":{"type":"polygon","count":1,"sensorMap":{"fisheye_front_left_rear_right_bev":{"sensorId":"fisheye_front_left_rear_right_bev","type":"fisheye_front_left_rear_right_bev","count":1,"objectCountByType":{"lane_fisheye_front_left_rear_right_bev_box":{"type":"lane_fisheye_front_left_rear_right_bev_box","count":1,"objectCountByGenerateMode":{"1":{"generateMode":1,"count":1,"objectCountByCheckResult":{"qualified":{"checkResult":"qualified","count":1,"detectionCount":0,"noneDetectionCount":0}}}}}}}}}}},"15":{"groupId":"15","type":"lane","count":1,"geometryMap":{"polygon":{"type":"polygon","count":1,"sensorMap":{"fisheye_front_left_rear_right_bev":{"sensorId":"fisheye_front_left_rear_right_bev","type":"fisheye_front_left_rear_right_bev","count":1,"objectCountByType":{"lane_fisheye_front_left_rear_right_bev_box":{"type":"lane_fisheye_front_left_rear_right_bev_box","count":1,"objectCountByGenerateMode":{"1":{"generateMode":1,"count":1,"objectCountByCheckResult":{"qualified":{"checkResult":"qualified","count":1,"detectionCount":0,"noneDetectionCount":0}}}}}}}}}}},"16":{"groupId":"16","type":"lane","count":1,"geometryMap":{"polygon":{"type":"polygon","count":1,"sensorMap":{"fisheye_front_left_rear_right_bev":{"sensorId":"fisheye_front_left_rear_right_bev","type":"fisheye_front_left_rear_right_bev","count":1,"objectCountByType":{"lane_fisheye_front_left_rear_right_bev_box":{"type":"lane_fisheye_front_left_rear_right_bev_box","count":1,"objectCountByGenerateMode":{"1":{"generateMode":1,"count":1,"objectCountByCheckResult":{"qualified":{"checkResult":"qualified","count":1,"detectionCount":0,"noneDetectionCount":0}}}}}}}}}}},"17":{"groupId":"17","type":"ignore","count":1,"geometryMap":{"polygon":{"type":"polygon","count":1,"sensorMap":{"fisheye_front_left_rear_right_bev":{"sensorId":"fisheye_front_left_rear_right_bev","type":"fisheye_front_left_rear_right_bev","count":1,"objectCountByType":{"ignore_fisheye_front_left_rear_right_bev_box":{"type":"ignore_fisheye_front_left_rear_right_bev_box","count":1,"objectCountByGenerateMode":{"1":{"generateMode":1,"count":1,"objectCountByCheckResult":{"qualified":{"checkResult":"qualified","count":1,"detectionCount":0,"noneDetectionCount":0}}}}}}}}}}},"18":{"groupId":"18","type":"stop_line","count":1,"geometryMap":{"polygon":{"type":"polygon","count":1,"sensorMap":{"fisheye_front_left_rear_right_bev":{"sensorId":"fisheye_front_left_rear_right_bev","type":"fisheye_front_left_rear_right_bev","count":1,"objectCountByType":{"stop_line_fisheye_front_left_rear_right_bev_box":{"type":"stop_line_fisheye_front_left_rear_right_bev_box","count":1,"objectCountByGenerateMode":{"1":{"generateMode":1,"count":1,"objectCountByCheckResult":{"qualified":{"checkResult":"qualified","count":1,"detectionCount":0,"noneDetectionCount":0}}}}}}}}}}}}}]}}